mwstreaming
